LICENSE
README.md
setup.py
NlpToolkit_Util.egg-info/PKG-INFO
NlpToolkit_Util.egg-info/SOURCES.txt
NlpToolkit_Util.egg-info/dependency_links.txt
NlpToolkit_Util.egg-info/top_level.txt
Util/FileUtils.py
Util/Interval.py
Util/Permutation.py
Util/RandomArray.py
Util/Subset.py
Util/SubsetFromList.py
Util/Swap.py
Util/__init__.py