Metadata-Version: 2.1
Name: NlpToolkit-Util
Version: 1.0.11
Summary: Simple Utils
Home-page: https://github.com/StarlangSoftware/Util-Py
Author: olcaytaner
Author-email: olcay.yildiz@ozyegin.edu.tr
License: UNKNOWN
Platform: UNKNOWN
